LICENSE.md
MANIFEST.in
README.md
requirements.txt
setup.py
assets/logo2.png
maidi/__init__.py
maidi/chords_symbols.py
maidi/constants.py
maidi/instrument.py
maidi/midi_library.py
maidi/score.py
maidi.egg-info/PKG-INFO
maidi.egg-info/SOURCES.txt
maidi.egg-info/dependency_links.txt
maidi.egg-info/requires.txt
maidi.egg-info/top_level.txt
maidi/analysis/__init__.py
maidi/analysis/analyze.py
maidi/analysis/parse_notes.py
maidi/analysis/tag_manager.py
maidi/analysis/tags.py
maidi/analysis/tags_providers.py
maidi/analysis/control_features/__init__.py
maidi/analysis/control_features/density.py
maidi/analysis/control_features/polyphony.py
maidi/analysis/control_features/properties.py
maidi/analysis/control_features/register.py
maidi/analysis/control_features/special_notes.py
maidi/analysis/metrics/__init__.py
maidi/analysis/metrics/generation_metric.py
maidi/chords/__init__.py
maidi/chords/chord_inference.py
maidi/chords/chord_inference_utils.py
maidi/chords/chord_manager.py
maidi/chords/chord_analyzer/__init__.py
maidi/chords/chord_analyzer/chord_analyzer.py
maidi/chords/chord_analyzer/chord_constants.py
maidi/examples/__init__.py
maidi/examples/ambient_chords.mid
maidi/examples/drum_and_bass.mid
maidi/examples/example1.mid
maidi/examples/pop_progression.mid
maidi/integrations/__init__.py
maidi/integrations/base.py
maidi/integrations/api/__init__.py
maidi/integrations/api/musiclang/__init__.py
maidi/integrations/api/musiclang/models.py
maidi/integrations/api/musiclang/musiclang.py
maidi/integrations/open_source/__init__.py
maidi/integrations/open_source/musiclang/__init__.py
maidi/metadata/pitch_classes_dict.pkl
maidi/metadata/pitches_dict.pkl
maidi/metadata/pitches_dict_roots.pkl
maidi/parser/__init__.py
maidi/parser/parser.py
maidi/tests/__init__.py
maidi/tests/test_bar_helpers.py
maidi/tests/test_chord_analyzer.py
maidi/tests/test_chord_inference.py
maidi/tests/test_chord_manager.py
maidi/tests/test_get_density.py
maidi/tests/test_metrics.py
maidi/tests/test_midi_library.py
maidi/tests/test_midi_score.py
maidi/tests/test_midi_score_utils.py
maidi/tests/test_min_max_polyphony.py
maidi/tests/test_parse_notes.py
