Metadata-Version: 2.1
Name: maidi
Version: 0.15.0
Summary: A python package for symbolic AI music inference
Author: Florian GARDIN
Author-email: fgardin.pro@gmail.com
License-File: LICENSE.md
Requires-Dist: symusic==0.4.7
Requires-Dist: scipy
Requires-Dist: requests
